Lab 05_Part1/Part1.v
// alu module
module alu(DATA1, DATA2, RESULT, SELECT);
input [7:0] DATA1 , DATA2; // set data1 and data2 as 8 bit inputs
input [2:0] SELECT; // set select as 3 bit input
output reg [7:0] RESULT; // set result as 8 bit output register

// Initialize 8 bit wires for storing outputs of the functional modules. 
wire  [7:0] forward_o , add_o , and_o , or_o;


// create instances of each functional modules.
FORWARD forward (DATA2, forward_o); 
ADD add_ (DATA1 , DATA2, add_o); 
AND and_ (DATA1 , DATA2, and_o); 
OR or_ (DATA1 , DATA2, or_o);   


/* always block
   If output of any functional module instance changed (forward_o , add_o , and_o , or_o)
   this block will be executed.
*/ 
always @ (forward_o , add_o , and_o , or_o , SELECT)
    begin
    
        case (SELECT)
            3'b000: // If SELECT == 0
                begin
                    RESULT =  forward_o; // assign value of forward_o to RESULT
                end
                
            3'b001: // If SELECT == 1
                begin
                    RESULT =  add_o; // assign value of add_o to RESULT
                end
                
            3'b010: // If SELECT == 2
                begin
                    RESULT = and_o; // assign value of and_o to RESULT
                end
                
            3'b011: // If SELECT == 3
                begin
                    RESULT = or_o; // assign value of or_o to RESULT
                end
                
        endcase
    end
endmodule  


// FORWARD funtional module
module FORWARD(DATA2, RESULT);
input [7:0] DATA2 ; // set data2 as 8 bit input
output [7:0] RESULT; // set result as 8 bit output
// set result as 8 bit register.
reg [7:0] RESULT; 

/* always block
   Sensitivity list contains DATA2
   When DATA2 changes this block will be executed.
*/
always @ (DATA2)
        RESULT = #1 DATA2; // After 1 unit data2 will be assigned to result
endmodule  


// ADD funtional module
module ADD(DATA1, DATA2, RESULT);
input [7:0] DATA1 , DATA2; // set data1 and data2 as 8 bit inputs
output [7:0] RESULT; // set result as 8 bit output
reg [7:0] RESULT; // set result as 8 bit register.                               

/* always block
   Sensitivity list contains DATA1 and DATA2
   When DATA1 or DATA2 changes this block will be executed.
*/
always @ (DATA1, DATA2)
    RESULT = #2 DATA1 + DATA2; // After 2 units data + data2 will be assigned to result
endmodule 


// AND funtional module
module AND(DATA1, DATA2, RESULT);
input [7:0] DATA1 , DATA2; // set data1 and data2 as 8 bit inputs
output [7:0] RESULT; // set result as 8 bit output
reg [7:0] RESULT; // set result as 8 bit register                             

/* always block
   Sensitivity list contains DATA1 and DATA2
   When DATA1 or DATA2 changes this block will be executed.
*/
always @ (DATA1, DATA2)
    RESULT = #1 DATA1 & DATA2; // After 1 units data & data2 will be assigned to result
endmodule 

// OR funtional module
module OR(DATA1, DATA2, RESULT);
input [7:0] DATA1 , DATA2; // set data1 and data2 as 8 bit inputs
output [7:0] RESULT; // set result as 8 bit output
reg [7:0] RESULT; // set result as 8 bit register

/* always block
   Sensitivity list contains DATA1 and DATA2
   When DATA1 or DATA2 changes this block will be executed.
*/
always @ (DATA1, DATA2)
    RESULT = #1 DATA1 | DATA2; // After 1 units data | data2 will be assigned to result
endmodule 



// Test bench module for testing purposes
module Testbench; 
    /* data1 , data2 , select are registers. 
       They are used to give inputs for the alu module.
    */
    reg [7:0] data1 , data2; 
    reg [2:0] select; 

    // result is a 8 bit wire. This is used as the output of the alu module.
    wire [7:0] result; 
    
    // create instance of the alu module.
    alu alu_t (data1 , data2 , result , select); 
    
    /* Initail block
       This is used to change values of the input ports.
    */
    initial 
    begin
        // t = 0    data1 = 0   data2 = 0   select = 0 (FORWARD)
        data1 = 8'b00000000 ; data2 = 8'b00000000 ; select = 3'b000; 


        #5 
        // t = 5    data1 = 4   data2 = 6   select = 0 (FORWARD)
        data1 = 8'b00000100 ; data2 = 8'b00000110 ; select = 3'b000;

        #5 
        // t = 10    data1 = 4   data2 = 5   select = 1 (ADD)
        data1 = 8'b00000100 ; data2 = 8'b00000101 ; select = 3'b001;

        #5 
        // t = 15    data1 = 5   data2 = 2   select = 2 (AND)
        data1 = 8'b00000101 ; data2 = 8'b00000010 ; select = 3'b010;

        #5 
        // t = 20    data1 = 6   data2 = 6   select = 3 (OR)
        data2 = 8'b00000110 ; data1 = 8'b00000110 ; select = 3'b011;
    end 
    

    /* Initial block
       This is used for monitoring purposes.
    */
    initial  
    begin
        $monitor("%d,\t%b,\t%b,\t%b,\t%b",$time, data1,data2,select,result); 
        // $monitor("%d,\t%d,\t%d,\t%d,\t%d",$time, data1,data2,select,result); 
        $dumpfile ("simple_processor.vcd"); 
        $dumpvars; 
    end 
        
endmodule

Lab 05_Part1/simple_processor.vcd
$date
	Wed Oct 21 09:43:45 2020
$end
$version
	Icarus Verilog
$end
$timescale
	1s
$end
$scope module Testbench $end
$var wire 8 ! result [7:0] $end
$var reg 8 " data1 [7:0] $end
$var reg 8 # data2 [7:0] $end
$var reg 3 $ select [2:0] $end
$scope module alu_t $end
$var wire 8 % DATA1 [7:0] $end
$var wire 8 & DATA2 [7:0] $end
$var wire 3 ' SELECT [2:0] $end
$var wire 8 ( or_o [7:0] $end
$var wire 8 ) forward_o [7:0] $end
$var wire 8 * and_o [7:0] $end
$var wire 8 + add_o [7:0] $end
$var reg 8 , RESULT [7:0] $end
$scope module add_ $end
$var wire 8 - DATA1 [7:0] $end
$var wire 8 . DATA2 [7:0] $end
$var reg 8 / RESULT [7:0] $end
$upscope $end
$scope module and_ $end
$var wire 8 0 DATA1 [7:0] $end
$var wire 8 1 DATA2 [7:0] $end
$var reg 8 2 RESULT [7:0] $end
$upscope $end
$scope module forward $end
$var wire 8 3 DATA2 [7:0] $end
$var reg 8 4 RESULT [7:0] $end
$upscope $end
$scope module or_ $end
$var wire 8 5 DATA1 [7:0] $end
$var wire 8 6 DATA2 [7:0] $end
$var reg 8 7 RESULT [7:0] $end
$upscope $end
$upscope $end
$upscope $end
$enddefinitions $end
#0
$dumpvars
bx 7
b0 6
b0 5
bx 4
b0 3
bx 2
b0 1
b0 0
bx /
b0 .
b0 -
bx ,
bx +
bx *
bx )
bx (
b0 '
b0 &
b0 %
b0 $
b0 #
b0 "
bx !
$end
#1
b0 !
b0 ,
b0 )
b0 4
b0 (
b0 7
b0 *
b0 2
#2
b0 +
b0 /
#5
b110 #
b110 &
b110 .
b110 1
b110 3
b110 6
b100 "
b100 %
b100 -
b100 0
b100 5
#6
b110 !
b110 ,
b110 )
b110 4
b100 *
b100 2
b110 (
b110 7
#7
b1010 +
b1010 /
#10
b1010 !
b1010 ,
b1 $
b1 '
b101 #
b101 &
b101 .
b101 1
b101 3
b101 6
#11
b101 (
b101 7
b101 )
b101 4
#12
b1001 !
b1001 ,
b1001 +
b1001 /
#15
b100 !
b100 ,
b10 $
b10 '
b10 #
b10 &
b10 .
b10 1
b10 3
b10 6
b101 "
b101 %
b101 -
b101 0
b101 5
#16
b0 !
b0 ,
b10 )
b10 4
b0 *
b0 2
b111 (
b111 7
#17
b111 +
b111 /
#20
b111 !
b111 ,
b11 $
b11 '
b110 "
b110 %
b110 -
b110 0
b110 5
b110 #
b110 &
b110 .
b110 1
b110 3
b110 6
#21
b110 !
b110 ,
b110 (
b110 7
b110 *
b110 2
b110 )
b110 4
#22
b1100 +
b1100 /
