Lab 05_Part2/Part1.v
// alu module
module alu(DATA1, DATA2, RESULT, SELECT);
input [7:0] DATA1 , DATA2; // set data1 and data2 as 8 bit inputs
input [2:0] SELECT; // set select as 3 bit input
output reg [7:0] RESULT; // set result as 8 bit output register

// Initialize 8 bit wires for storing outputs of the functional modules. 
wire  [7:0] forward_o , add_o , and_o , or_o;


// create instances of each functional modules.
FORWARD forward (DATA2, forward_o); 
ADD add_ (DATA1 , DATA2, add_o); 
AND and_ (DATA1 , DATA2, and_o); 
OR or_ (DATA1 , DATA2, or_o);   


/* always block
   If output of any functional module instance changed (forward_o , add_o , and_o , or_o)
   this block will be executed.
*/ 
always @ (forward_o , add_o , and_o , or_o , SELECT)
    begin
    
        case (SELECT)
            3'b000: // If SELECT == 0
                begin
                    RESULT =  forward_o; // assign value of forward_o to RESULT
                end
                
            3'b001: // If SELECT == 1
                begin
                    RESULT =  add_o; // assign value of add_o to RESULT
                end
                
            3'b010: // If SELECT == 2
                begin
                    RESULT = and_o; // assign value of and_o to RESULT
                end
                
            3'b011: // If SELECT == 3
                begin
                    RESULT = or_o; // assign value of or_o to RESULT
                end
                
        endcase
    end
endmodule  


// FORWARD funtional module
module FORWARD(DATA2, RESULT);
input [7:0] DATA2 ; // set data2 as 8 bit input
output [7:0] RESULT; // set result as 8 bit output
// set result as 8 bit register.
// reg [7:0] RESULT; 

/* always block
   Sensitivity list contains DATA2
   When DATA2 changes this block will be executed.
*/
// always @ (DATA2)
//         #1 RESULT = DATA2; // After 1 unit data2 will be assigned to result
assign #1 RESULT = DATA2;
endmodule  


// ADD funtional module
module ADD(DATA1, DATA2, RESULT);
input [7:0] DATA1 , DATA2; // set data1 and data2 as 8 bit inputs
output [7:0] RESULT; // set result as 8 bit output
// reg [7:0] RESULT; // set result as 8 bit register.                               

/* always block
   Sensitivity list contains DATA1 and DATA2
   When DATA1 or DATA2 changes this block will be executed.
*/
// always @ (DATA1, DATA2)
//     #2 RESULT = DATA1 + DATA2; // After 2 units data + data2 will be assigned to result
assign #2 RESULT = DATA1 + DATA2;
endmodule 


// AND funtional module
module AND(DATA1, DATA2, RESULT);
input [7:0] DATA1 , DATA2; // set data1 and data2 as 8 bit inputs
output [7:0] RESULT; // set result as 8 bit output
// reg [7:0] RESULT; // set result as 8 bit register                             

/* always block
   Sensitivity list contains DATA1 and DATA2
   When DATA1 or DATA2 changes this block will be executed.
*/
// always @ (DATA1, DATA2)
//     #1 RESULT = DATA1 & DATA2; // After 1 units data & data2 will be assigned to result
assign #1 RESULT = DATA1 & DATA2;
endmodule 

// OR funtional module
module OR(DATA1, DATA2, RESULT);
input [7:0] DATA1 , DATA2; // set data1 and data2 as 8 bit inputs
output [7:0] RESULT; // set result as 8 bit output
// reg [7:0] RESULT; // set result as 8 bit register

/* always block
   Sensitivity list contains DATA1 and DATA2
   When DATA1 or DATA2 changes this block will be executed.
*/
// always @ (DATA1, DATA2)
//     #1 RESULT = DATA1 | DATA2; // After 1 units data | data2 will be assigned to result
assign #1 RESULT = DATA1 | DATA2;
endmodule 



// // Test bench module for testing purposes
// module Testbench; 
//     /* data1 , data2 , select are registers. 
//        They are used to give inputs for the alu module.
//     */
//     reg [7:0] data1 , data2; 
//     reg [2:0] select; 

//     // result is a 8 bit wire. This is used as the output of the alu module.
//     wire [7:0] result; 
    
//     // create instance of the alu module.
//     alu alu_t (data1 , data2 , result , select); 
    
//     /* Initail block
//        This is used to change values of the input ports.
//     */
//     initial 
//     begin
//         // t = 0    data1 = 0   data2 = 0   select = 0 (FORWARD)
//         data1 = 8'b00000000 ; data2 = 8'b00000000 ; select = 3'b000; 


//         #5 
//         // t = 5    data1 = 4   data2 = 6   select = 0 (FORWARD)
//         data1 = 8'b00000100 ; data2 = 8'b00000110 ; select = 3'b000;

//         #5 
//         // t = 10    data1 = 4   data2 = 5   select = 1 (ADD)
//         data1 = 8'b00000100 ; data2 = 8'b00000101 ; select = 3'b001;

//         #5 
//         // t = 15    data1 = 5   data2 = 2   select = 2 (AND)
//         data1 = 8'b00000101 ; data2 = 8'b00000010 ; select = 3'b010;

//         #5 
//         // t = 20    data1 = 6   data2 = 6   select = 3 (OR)
//         data2 = 8'b00000110 ; data1 = 8'b00000110 ; select = 3'b011;
//     end 
    

//     /* Initial block
//        This is used for monitoring purposes.
//     */
//     initial  
//     begin
//         $monitor("%d,\t%b,\t%b,\t%b,\t%b",$time, data1,data2,select,result); 
//         // $monitor("%d,\t%d,\t%d,\t%d,\t%d",$time, data1,data2,select,result); 
//         $dumpfile ("simple_processor.vcd"); 
//         $dumpvars; 
//     end 
        
// endmodule

Lab 05_Part2/Part2.v
// reg_file module
module reg_file(IN,OUT1,OUT2,INADDRESS,OUT1ADDRESS,OUT2ADDRESS, WRITE, CLK, RESET);
input [7:0] IN; // set IN as 8 bit input
input [2:0] INADDRESS , OUT1ADDRESS , OUT2ADDRESS; // set INADDRESS , OUT1ADDRESS , OUT2ADDRESS as 3 bit inputs
input WRITE , CLK , RESET; // set WRITE , CLK , RESET as inputs
output reg [7:0] OUT1 , OUT2; // set OUT1 , OUT2 as 8 bit output registers

reg [7:0] registers [7:0]; // Create 8 , 8 bit registers to store values.

integer i; // Initialize a integer variable for loop

/* always block
   This block will be executed when rising edge of CLK occurs.
*/
always @ (posedge CLK)
begin
    if(RESET)begin // If RESET = 1
        /* all the registers will be set as 0
           This is a non blocking statement. So all the registers will be set as 0
           at same time (after 1 time unit).
        */
        for (i=0;i<=7;i=i+1)begin
            registers[i] <=  #1 0;   
        end  
    end

    // If RESET == 0 and WRITE == 1
    if(!RESET & WRITE)begin
        /* store given value in the given register.
           IN contains the value and INADDRESS used to identify the register.
        */
        registers[INADDRESS] <= #1 IN; 
    end  
end


/* always block
   This block will be executed when OUT1 or OUT2 or RESET or WRITE changed
*/
always @ (OUT1ADDRESS , OUT2ADDRESS , RESET , WRITE)
begin
    if(!WRITE)begin // If WRITE == 0
        OUT1 <= #2 registers[OUT1ADDRESS]; // set OUT1 as the value in OUT1ADDRESS register
        OUT2 <= #2 registers[OUT2ADDRESS]; // set OUT2 as the value in OUT2ADDRESS register
    end
    
end
endmodule  


// // Testbench module for testing purposes
// module Testbench; 

//     /* Following wires and registers are used to create instance of the reg_file module.
//     */
//     reg [7:0] IN; // IN is a 8 bit register
//     reg [2:0] INADDRESS , OUT1ADDRESS , OUT2ADDRESS; // INADDRESS , OUT1ADDRESS , OUT2ADDRESS are 3 bit registers
//     reg WRITE , CLK , RESET; // WRITE , CLK , RESET are registers
//     wire [7:0] OUT1 , OUT2; // OUT1 , OUT2 are 8 bit wires

//     // create instance of the reg_file module
//     reg_file reg_f (IN,OUT1,OUT2,INADDRESS,OUT1ADDRESS,OUT2ADDRESS, WRITE, CLK, RESET);
    
//     initial 
//     begin
        
//         // t = 5
//         #5 RESET = 1; CLK = 0; CLK = 1; RESET = 0; // Reset
//         // t = 10
//         #5 WRITE = 1; CLK = 0; CLK = 1; IN = 10; INADDRESS = 0; // register0 value = 10
//         // t = 15
//         #5 CLK = 0; CLK = 1; IN = 20; INADDRESS = 1; // register1 value = 20
//         // t = 20
//         #5 CLK = 0; CLK = 1; IN = 30; INADDRESS = 2; // register2 value = 30
//         // t = 25
//         #5 CLK = 0; CLK = 1; IN = 40; INADDRESS = 3; // register4 value = 10
//         // t = 30
//         #5 CLK = 0; CLK = 1; IN = 50; INADDRESS = 4; // register5 value = 10
//         // t = 35
//         #5 CLK = 0; CLK = 1; IN = 60; INADDRESS = 5; // register6 value = 10
//         // t = 40
//         #5 CLK = 0; CLK = 1; IN = 70; INADDRESS = 6; // register7 value = 10
//         // t = 45
//         #5 CLK = 0; CLK = 1; IN = 80; INADDRESS = 7; // register8 value = 10


//         // t = 50
//         #5 WRITE = 0; OUT1ADDRESS = 0; OUT2ADDRESS = 1; // get register1 and register2 value
//         // t = 55
//         #5 OUT1ADDRESS = 2; OUT2ADDRESS = 3; // get register3 and register4 value
//         // t = 60
//         #5 OUT1ADDRESS = 4; OUT2ADDRESS = 5; // get register5 and register6 value
//         // t = 65
//         #5 OUT1ADDRESS = 6; OUT2ADDRESS = 7; // get register7 and register8 value


//         // t = 70
//         #5 WRITE = 1; RESET = 1; CLK = 0; CLK = 1; // reset
//         // t = 75
//         #5 RESET = 0; WRITE = 0; OUT1ADDRESS = 0; OUT2ADDRESS = 1;
//     end 


//     /* Initial block
//        This is used for monitoring purposes.
//     */
//     initial  
//     begin
//         $monitor("%d,\t%d,\t%d,\t%d,\t%d,\t%d,\t%d,\t%d,\t%d,\t%d",$time, IN,INADDRESS,OUT1ADDRESS,OUT2ADDRESS,WRITE,CLK, RESET,OUT1,OUT2); 
//         // $monitor("%d,\t%d,\t%d",$time,OUT1,OUT2); 
//         $dumpfile ("register_file.vcd"); 
//         $dumpvars; 
//     end 
    
// endmodule

Lab 05_Part2/Part3.v
`include "Part1.v"
`include "Part2.v"
// CPU module
module cpu(PC, INSTRUCTION, CLK, RESET);
    
    output reg [31:0] PC;               //Register to hold the PC address
    input [31:0] INSTRUCTION;           //Fetching instruction to the cpu as a input
    input CLK, RESET;                   //Clok and the Reset to clear the cpu

    wire [31:0] PC_Reg;                 // PC adder(To hold the current PC + 4)

    PC_Adder pc_adder (PC_Reg , PC);    //Insatance of a PC_Adder module to increase the Current PC by 4(PC = PC+4)


    // MUX_ Selections(Registers to hold the value come from the two muxes in the cpu)
    reg [7:0] MUX_1_OUT;        //(MUX 1 :- To get the REGOUT2 value or the 2s complement of REGOUT2)
    reg [7:0] MUX_2_OUT ;       //(MUX 2 :- to get the Immediate value from the corresponding instruction or 
                                //get the output of MUX 1)



//===========================================================================================================================
    //always block for update the PC value(PC UPDATE) and if RESET signal given as 1 ,then to reset the cpu(Bring the PC to 0)
    always @(posedge CLK) 
    begin

        if (RESET == 1) begin
            PC <= #1 0;         //Set the PC value to 0 (begin) if RESET Signal is given
        end

        else begin
            PC = #1 PC_Reg;     //Otherwise update the pc(PC UPDATE) with the ouptput of PC adder(PC = PC + 4)
        end

    end
//============================================================================================================================  
    
    
    // Decode(To Decode and Identify the INSTRUCTION into parts [OPCODE],[RD/IMM],[RT],[RS/IMM])

    //Control signals of MUX 1 nad MUX 2
    reg SELECT1;            //Control signal Of MUX 1
    reg SELECT2;            //Control signal of MUX 2
    
    
    reg [2:0] SELECT;       //The signal of ALUOP (to get the corresponding operation's reslut)
    wire [7:0] RESULT;      //The Output of The ALU

    /*

        | OP-CODE      |  RD / IMM      | RT            |  RS / IMM  |
        | (bits 31-24) |  (bits 23-16)  | (bits 15-8)   |  (bits7-0) |
        
    */
    
    //To check the OPCODE of the instruction word and update the SELECT,SELECT1 and SELECT2
    always @(INSTRUCTION) 
    begin
        case (INSTRUCTION[31:24]) //OPCODE part of the given Instruction
            8'b00000000:    // Loadi
                begin
                    SELECT <= #1 0;     //change the SELECT (ALUOP) to 000(FORWARD)
                end
                
            8'b00000001: // Mov
                begin
                    SELECT <= #1 0;     //Change the SELECT (ALOUP) to 000(FORWARD) 
                end
            
            8'b00000010: // Add
                begin
                    SELECT <= #1 1;     //change the SELECT (ALUOP) to 001(ADD)
                end
            
            8'b00000011: // Sub
                begin
                    SELECT <= #1 1;     //change the SELECT (ALUOP) to 001(ADD)
                end

            8'b00000100: // And
                begin
                    SELECT <= #1 2;     //change the SELECT (ALUOP) to 010(AND)
                end
            
            8'b00000101: // Or
                begin
                    SELECT <= #1 3;     //change the SELECT (ALUOP) to 011(OR)
                end

        endcase


        /*
        SELECT     =>   Supported Instructions
        --------------------------------------
        FORWARD    =>   loadi,mov
        ADD        =>   add,sub
        AND        =>   and
        OR         =>   or
        --------------------------------------
        */
        

        // MUX1 (To check the opcode of the given instruction and UPdate the MUX1's SELECT1 signal)
        
        if (INSTRUCTION[31:24] == 3) begin      // SUB (Check that opcode value is equal the SUB instruction)
            SELECT1 <= #1 1;                    //If its true , set SELECT1 = 1 (To get the 2's compliment of REGOUT2)
        end

        else begin                              //For other opcodes SELECT1 = 0 
            SELECT1 <= #1 0;
        end


        // MUX2 (To check the opcode of the given instruction and UPdate the MUX2's SELECT2 signal )

        if (INSTRUCTION[31:24] == 0) begin      // LOADI (Check whether given instruction's opcode is for loadi )
            SELECT2 <= #1 0;                    //If it is true  SELECT2 = 0,(To get the IMM value) 
        end

        else begin
            SELECT2 <= #1 1;                    //For other opcodes SELECT2 =1(To het the ouput of MUX1)
        end

        

    end

    always @(posedge CLK) 
    begin
        #1 WRITE = 0;
        #4 WRITE = 1;
    end


    // REGISTER READ

    // Register file instance
    reg [7:0] IN;               // IN is a 8 bit register
    reg WRITE;                  // WRITE is a register
    wire [7:0] OUT1 , OUT2;     // OUT1 , OUT2 are 8 bit wires
    
    // create instance of the reg_file module
    reg_file reg_f (RESULT,OUT1,OUT2,INSTRUCTION[18:16],INSTRUCTION[10:8],INSTRUCTION[2:0], WRITE, CLK, RESET);
    /* 
    
    *This take the relevant part of the Instruction as READREG1,READREG2 and  WRITEREG(Also with the WRITE,CLK,and RESET)
    *Then read the values from the corresponding registers and put them into OUT1 and OUT2
    *Also at the write time the RESULT (IN) of the ALU write to the Correspondung register

    */
    
    // 2'S COMPLEMENT INSTANCE
    wire [7:0] COMP_OUTPUT;
    TWO_COMP two_comp (OUT2 , COMP_OUTPUT); 

    
    // MUX_1 Selection
    always @(OUT2 , COMP_OUTPUT) begin
        if(SELECT1 == 0)begin
            MUX_1_OUT = OUT2;               //If the SELECT1 = 0 then set MUX_1_OUT as REGOUT2
        end
        else begin
            MUX_1_OUT = COMP_OUTPUT;        //Otherwise Set the MUX_1_OUT as 2's compliment of REGOUT2
        end
    end

    // MUX_2 Selection(To get the output of the MUX2)
    always @(MUX_1_OUT , INSTRUCTION[7:0] , SELECT2) begin
        if(SELECT2 == 0)begin
            MUX_2_OUT = INSTRUCTION[7:0];   //If SELECT2 == 0 then the corresponding value send through the mux 2(IMM value)
        end
        else begin
            MUX_2_OUT = MUX_1_OUT;          //Otherwise send the output of the MUX1
        end
    end


    //Create instance of the alu
    alu alu_(OUT1, MUX_2_OUT, RESULT, SELECT);
    /*
        *ALU get OUT1(REGOUT1 from the register file) as [OPERAND 1] and MUX_2OUT(Output of the MUX2) as the o[OPERAND 2]
        *SELECT signal is updated to the correponding value by control unit.Therefor ALU Produce the RESULT and give it 
        to the IN(IN of the register file)

    */ 

endmodule 

//Adder for update the value of current pc  value

module PC_Adder(PC_Reg , PC);
    output reg [31:0] PC_Reg;       //To old the value of PC = PC +4
    input [31:0] PC;                //Take the current PC value as the INPUT
    always @(PC) 
    begin
        PC_Reg = #1 PC + 4;         //UPDATE the pc to PC +4 
    end
endmodule


//Module to get the 2's compliment of a given 8 bit value
module TWO_COMP (COMP_INPUT , COMP_OUTPUT);
    input [7:0] COMP_INPUT;         //Input(8 bit number)
    output [7:0] COMP_OUTPUT;       //Output(2's compliment of the given  number)

    assign #1 COMP_OUTPUT = ~ COMP_INPUT + 8'b00000001; //Turn the given value to its 2's compliment
endmodule


module cpu_tb;

    reg CLK, RESET;
    wire [31:0] PC;
    wire [31:0] INSTRUCTION;
    
    /* 
    ------------------------
     SIMPLE INSTRUCTION MEM
    ------------------------
    */
    
    // TODO: Initialize an array of registers (8x1024) named 'instr_mem' to be used as instruction memory
    reg [7:0] instr_mem [1023:0];

    
    // TODO: Create combinational logic to support CPU instruction fetching, given the Program Counter(PC) value 
    //       (make sure you include the delay for instruction fetching here)

    assign #2 INSTRUCTION = {instr_mem[PC+3],instr_mem[PC+2],instr_mem[PC+1],instr_mem[PC+0]};
    
    initial
    begin
        // PC = 0;
        // Initialize instruction memory with the set of instructions you need execute on CPU
        
        // METHOD 1: manually loading instructions to instr_mem
        // {instr_mem[10'd3], instr_mem[10'd2], instr_mem[10'd1], instr_mem[10'd0]} = 32'b00000000000001000000000000000101;
        //{instr_mem[10'd7], instr_mem[10'd6], instr_mem[10'd5], instr_mem[10'd4]} = 32'b00000000000000100000000000001001;
        //{instr_mem[10'd11], instr_mem[10'd10], instr_mem[10'd9], instr_mem[10'd8]} = 32'b00000010000001100000010000000010;
        
        // METHOD 2: loading instr_mem content from instr_mem.mem file
        $readmemb("instr_mem.mem", instr_mem);
    end
    
    /* 
    -----
     CPU
    -----
    */
    cpu mycpu(PC, INSTRUCTION, CLK, RESET);

    initial
    begin
    
        // generate files needed to plot the waveform using GTKWave
        $dumpfile("cpu_wavedata.vcd");
		$dumpvars(0, mycpu);
        // $monitor("%d,\t%b,\t%b",$time,PC,INSTRUCTION); 
        
        // TODO: Reset the CPU (by giving a pulse to RESET signal) to start the program execution
        
        // finish simulation after some time
        #500
        $finish;
        
    end

    initial
    begin
        CLK = 1'b0;
        RESET = 1'b1;
        #10
        RESET = 1'b0;
    end
    
    // clock signal generation
    always
        #4 CLK = ~CLK;
    
endmodule

Lab 05_Part2/cpu_wavedata.vcd
$date
	Wed Oct 28 10:19:13 2020
$end
$version
	Icarus Verilog
$end
$timescale
	1s
$end
$scope module cpu_tb $end
$scope module mycpu $end
$var wire 1 ! CLK $end
$var wire 32 " INSTRUCTION [31:0] $end
$var wire 1 # RESET $end
$var wire 8 $ RESULT [7:0] $end
$var wire 32 % PC_Reg [31:0] $end
$var wire 8 & OUT2 [7:0] $end
$var wire 8 ' OUT1 [7:0] $end
$var wire 8 ( COMP_OUTPUT [7:0] $end
$var reg 8 ) MUX_1_OUT [7:0] $end
$var reg 8 * MUX_2_OUT [7:0] $end
$var reg 32 + PC [31:0] $end
$var reg 3 , SELECT [2:0] $end
$var reg 1 - SELECT1 $end
$var reg 1 . SELECT2 $end
$var reg 1 / WRITE $end
$scope module alu_ $end
$var wire 8 0 DATA2 [7:0] $end
$var wire 3 1 SELECT [2:0] $end
$var wire 8 2 or_o [7:0] $end
$var wire 8 3 forward_o [7:0] $end
$var wire 8 4 and_o [7:0] $end
$var wire 8 5 add_o [7:0] $end
$var wire 8 6 DATA1 [7:0] $end
$var reg 8 7 RESULT [7:0] $end
$scope module add_ $end
$var wire 8 8 DATA2 [7:0] $end
$var wire 8 9 RESULT [7:0] $end
$var wire 8 : DATA1 [7:0] $end
$upscope $end
$scope module and_ $end
$var wire 8 ; DATA2 [7:0] $end
$var wire 8 < RESULT [7:0] $end
$var wire 8 = DATA1 [7:0] $end
$upscope $end
$scope module forward $end
$var wire 8 > DATA2 [7:0] $end
$var wire 8 ? RESULT [7:0] $end
$upscope $end
$scope module or_ $end
$var wire 8 @ DATA2 [7:0] $end
$var wire 8 A RESULT [7:0] $end
$var wire 8 B DATA1 [7:0] $end
$upscope $end
$upscope $end
$scope module pc_adder $end
$var wire 32 C PC [31:0] $end
$var reg 32 D PC_Reg [31:0] $end
$upscope $end
$scope module reg_f $end
$var wire 1 ! CLK $end
$var wire 8 E IN [7:0] $end
$var wire 3 F INADDRESS [2:0] $end
$var wire 3 G OUT1ADDRESS [2:0] $end
$var wire 3 H OUT2ADDRESS [2:0] $end
$var wire 1 # RESET $end
$var wire 1 / WRITE $end
$var reg 8 I OUT1 [7:0] $end
$var reg 8 J OUT2 [7:0] $end
$var integer 32 K i [31:0] $end
$upscope $end
$scope module two_comp $end
$var wire 8 L COMP_INPUT [7:0] $end
$var wire 8 M COMP_OUTPUT [7:0] $end
$upscope $end
$upscope $end
$upscope $end
$enddefinitions $end
#0
$dumpvars
bx M
bx L
bx K
bx J
bx I
bx H
bx G
bx F
bx E
bx D
bx C
bx B
bx A
bx @
bx ?
bx >
bx =
bx <
bx ;
bx :
bx 9
bx 8
bx 7
bx 6
bx 5
bx 4
bx 3
bx 2
bx 1
bx 0
x/
x.
x-
bx ,
bx +
bx *
bx )
bx (
bx '
bx &
bx %
bx $
1#
bx "
0!
$end
#4
b1000 K
1!
#5
b0 +
b0 C
0/
#6
b100 %
b100 D
#7
b100 F
b0 G
b101 H
b1000000000000000101 "
#8
b101 *
b101 0
b101 8
b101 ;
b101 >
b101 @
0.
0-
b0 ,
b0 1
0!
#9
b0 )
b0 &
b0 J
b0 L
b0 '
b0 6
b0 :
b0 =
b0 B
b0 I
b101 $
b101 7
b101 E
b0x0x 4
b0x0x <
bx1x1 2
bx1x1 A
b101 3
b101 ?
1/
#10
b0 (
b0 M
b101 2
b101 A
b0 4
b0 <
0#
#11
b101 5
b101 9
#12
1!
#13
b100 +
b100 C
0/
#14
b1000 %
b1000 D
#15
b1001 *
b1001 0
b1001 8
b1001 ;
b1001 >
b1001 @
b10 F
b1 H
b100000000000001001 "
#16
b1001 $
b1001 7
b1001 E
b1001 2
b1001 A
b1001 3
b1001 ?
0!
#17
b1001 5
b1001 9
1/
#20
1!
#21
b1000 +
b1000 C
0/
#22
b1100 %
b1100 D
#23
b10 *
b10 0
b10 8
b10 ;
b10 >
b10 @
b110 F
b100 G
b10 H
b10000001100000010000000010 "
#24
b0 *
b0 0
b0 8
b0 ;
b0 >
b0 @
1.
b1 ,
b1 1
b1001 $
b1001 7
b1001 E
b10 2
b10 A
b10 3
b10 ?
0!
#25
b1001 *
b1001 0
b1001 8
b1001 ;
b1001 >
b1001 @
b1001 )
b1001 &
b1001 J
b1001 L
b101 '
b101 6
b101 :
b101 =
b101 B
b101 I
b0 2
b0 A
b0 3
b0 ?
1/
#26
b1 4
b1 <
b1001 3
b1001 ?
b11110111 (
b11110111 M
b1101 2
b1101 A
#27
b1110 $
b1110 7
b1110 E
b1110 5
b1110 9
#28
1!
#29
b1100 +
b1100 C
0/
#30
b10000 %
b10000 D
#31
b0 F
b0 G
b110 H
b1000000000000000000000110 "
#32
b1001 $
b1001 7
b1001 E
b0 ,
b0 1
0!
#33
b1110 *
b1110 0
b1110 8
b1110 ;
b1110 >
b1110 @
b1110 )
b1110 &
b1110 J
b1110 L
b0 '
b0 6
b0 :
b0 =
b0 B
b0 I
1/
#34
b1110 $
b1110 7
b1110 E
b1110 3
b1110 ?
b11110010 (
b11110010 M
b1110 2
b1110 A
b0 4
b0 <
#36
1!
#37
b10000 +
b10000 C
0/
#38
b10100 %
b10100 D
#39
b101 F
b1 H
b1010000000000000001 "
#40
b1 *
b1 0
b1 8
b1 ;
b1 >
b1 @
0.
0!
#41
b0 )
b0 &
b0 J
b0 L
b1110 '
b1110 6
b1110 :
b1110 =
b1110 B
b1110 I
b1 $
b1 7
b1 E
b1 2
b1 A
b1 3
b1 ?
1/
#42
b0 (
b0 M
b1111 2
b1111 A
#43
b1111 5
b1111 9
#44
1!
#45
b10100 +
b10100 C
0/
#46
b11000 %
b11000 D
#47
b101 *
b101 0
b101 8
b101 ;
b101 >
b101 @
b11 F
b10 G
b101 H
b11000000110000001000000101 "
#48
b0 *
b0 0
b0 8
b0 ;
b0 >
b0 @
1.
1-
b1 ,
b1 1
b1111 $
b1111 7
b1111 E
b100 4
b100 <
b101 3
b101 ?
0!
#49
b1 &
b1 J
b1 L
b1001 '
b1001 6
b1001 :
b1001 =
b1001 B
b1001 I
b0 4
b0 <
b1110 2
b1110 A
b0 3
b0 ?
1/
#50
b11111111 *
b11111111 0
b11111111 8
b11111111 ;
b11111111 >
b11111111 @
b11111111 )
b11111111 (
b11111111 M
b1001 2
b1001 A
#51
b1001 4
b1001 <
b11111111 2
b11111111 A
b11111111 3
b11111111 ?
#52
b1000 $
b1000 7
b1000 E
b1000 5
b1000 9
1!
#53
b11000 +
b11000 C
0/
#54
b11100 %
b11100 D
#55
bx F
bx G
bx H
bx "
#56
0-
0!
#57
bx *
bx 0
bx 8
bx ;
bx >
bx @
bx )
bx &
bx J
bx L
bx '
bx 6
bx :
bx =
bx B
bx I
1/
#58
bx 2
bx A
bx 3
bx ?
bx (
bx M
bx 4
bx <
#59
bx $
bx 7
bx E
bx 5
bx 9
#60
1!
#61
b11100 +
b11100 C
0/
#62
b100000 %
b100000 D
#64
0!
#65
1/
#68
1!
#69
b100000 +
b100000 C
0/
#70
b100100 %
b100100 D
#72
0!
#73
1/
#76
1!
#77
b100100 +
b100100 C
0/
#78
b101000 %
b101000 D
#80
0!
#81
1/
#84
1!
#85
b101000 +
b101000 C
0/
#86
b101100 %
b101100 D
#88
0!
#89
1/
#92
1!
#93
b101100 +
b101100 C
0/
#94
b110000 %
b110000 D
#96
0!
#97
1/
#100
1!
#101
b110000 +
b110000 C
0/
#102
b110100 %
b110100 D
#104
0!
#105
1/
#108
1!
#109
b110100 +
b110100 C
0/
#110
b111000 %
b111000 D
#112
0!
#113
1/
#116
1!
#117
b111000 +
b111000 C
0/
#118
b111100 %
b111100 D
#120
0!
#121
1/
#124
1!
#125
b111100 +
b111100 C
0/
#126
b1000000 %
b1000000 D
#128
0!
#129
1/
#132
1!
#133
b1000000 +
b1000000 C
0/
#134
b1000100 %
b1000100 D
#136
0!
#137
1/
#140
1!
#141
b1000100 +
b1000100 C
0/
#142
b1001000 %
b1001000 D
#144
0!
#145
1/
#148
1!
#149
b1001000 +
b1001000 C
0/
#150
b1001100 %
b1001100 D
#152
0!
#153
1/
#156
1!
#157
b1001100 +
b1001100 C
0/
#158
b1010000 %
b1010000 D
#160
0!
#161
1/
#164
1!
#165
b1010000 +
b1010000 C
0/
#166
b1010100 %
b1010100 D
#168
0!
#169
1/
#172
1!
#173
b1010100 +
b1010100 C
0/
#174
b1011000 %
b1011000 D
#176
0!
#177
1/
#180
1!
#181
b1011000 +
b1011000 C
0/
#182
b1011100 %
b1011100 D
#184
0!
#185
1/
#188
1!
#189
b1011100 +
b1011100 C
0/
#190
b1100000 %
b1100000 D
#192
0!
#193
1/
#196
1!
#197
b1100000 +
b1100000 C
0/
#198
b1100100 %
b1100100 D
#200
0!
#201
1/
#204
1!
#205
b1100100 +
b1100100 C
0/
#206
b1101000 %
b1101000 D
#208
0!
#209
1/
#212
1!
#213
b1101000 +
b1101000 C
0/
#214
b1101100 %
b1101100 D
#216
0!
#217
1/
#220
1!
#221
b1101100 +
b1101100 C
0/
#222
b1110000 %
b1110000 D
#224
0!
#225
1/
#228
1!
#229
b1110000 +
b1110000 C
0/
#230
b1110100 %
b1110100 D
#232
0!
#233
1/
#236
1!
#237
b1110100 +
b1110100 C
0/
#238
b1111000 %
b1111000 D
#240
0!
#241
1/
#244
1!
#245
b1111000 +
b1111000 C
0/
#246
b1111100 %
b1111100 D
#248
0!
#249
1/
#252
1!
#253
b1111100 +
b1111100 C
0/
#254
b10000000 %
b10000000 D
#256
0!
#257
1/
#260
1!
#261
b10000000 +
b10000000 C
0/
#262
b10000100 %
b10000100 D
#264
0!
#265
1/
#268
1!
#269
b10000100 +
b10000100 C
0/
#270
b10001000 %
b10001000 D
#272
0!
#273
1/
#276
1!
#277
b10001000 +
b10001000 C
0/
#278
b10001100 %
b10001100 D
#280
0!
#281
1/
#284
1!
#285
b10001100 +
b10001100 C
0/
#286
b10010000 %
b10010000 D
#288
0!
#289
1/
#292
1!
#293
b10010000 +
b10010000 C
0/
#294
b10010100 %
b10010100 D
#296
0!
#297
1/
#300
1!
#301
b10010100 +
b10010100 C
0/
#302
b10011000 %
b10011000 D
#304
0!
#305
1/
#308
1!
#309
b10011000 +
b10011000 C
0/
#310
b10011100 %
b10011100 D
#312
0!
#313
1/
#316
1!
#317
b10011100 +
b10011100 C
0/
#318
b10100000 %
b10100000 D
#320
0!
#321
1/
#324
1!
#325
b10100000 +
b10100000 C
0/
#326
b10100100 %
b10100100 D
#328
0!
#329
1/
#332
1!
#333
b10100100 +
b10100100 C
0/
#334
b10101000 %
b10101000 D
#336
0!
#337
1/
#340
1!
#341
b10101000 +
b10101000 C
0/
#342
b10101100 %
b10101100 D
#344
0!
#345
1/
#348
1!
#349
b10101100 +
b10101100 C
0/
#350
b10110000 %
b10110000 D
#352
0!
#353
1/
#356
1!
#357
b10110000 +
b10110000 C
0/
#358
b10110100 %
b10110100 D
#360
0!
#361
1/
#364
1!
#365
b10110100 +
b10110100 C
0/
#366
b10111000 %
b10111000 D
#368
0!
#369
1/
#372
1!
#373
b10111000 +
b10111000 C
0/
#374
b10111100 %
b10111100 D
#376
0!
#377
1/
#380
1!
#381
b10111100 +
b10111100 C
0/
#382
b11000000 %
b11000000 D
#384
0!
#385
1/
#388
1!
#389
b11000000 +
b11000000 C
0/
#390
b11000100 %
b11000100 D
#392
0!
#393
1/
#396
1!
#397
b11000100 +
b11000100 C
0/
#398
b11001000 %
b11001000 D
#400
0!
#401
1/
#404
1!
#405
b11001000 +
b11001000 C
0/
#406
b11001100 %
b11001100 D
#408
0!
#409
1/
#412
1!
#413
b11001100 +
b11001100 C
0/
#414
b11010000 %
b11010000 D
#416
0!
#417
1/
#420
1!
#421
b11010000 +
b11010000 C
0/
#422
b11010100 %
b11010100 D
#424
0!
#425
1/
#428
1!
#429
b11010100 +
b11010100 C
0/
#430
b11011000 %
b11011000 D
#432
0!
#433
1/
#436
1!
#437
b11011000 +
b11011000 C
0/
#438
b11011100 %
b11011100 D
#440
0!
#441
1/
#444
1!
#445
b11011100 +
b11011100 C
0/
#446
b11100000 %
b11100000 D
#448
0!
#449
1/
#452
1!
#453
b11100000 +
b11100000 C
0/
#454
b11100100 %
b11100100 D
#456
0!
#457
1/
#460
1!
#461
b11100100 +
b11100100 C
0/
#462
b11101000 %
b11101000 D
#464
0!
#465
1/
#468
1!
#469
b11101000 +
b11101000 C
0/
#470
b11101100 %
b11101100 D
#472
0!
#473
1/
#476
1!
#477
b11101100 +
b11101100 C
0/
#478
b11110000 %
b11110000 D
#480
0!
#481
1/
#484
1!
#485
b11110000 +
b11110000 C
0/
#486
b11110100 %
b11110100 D
#488
0!
#489
1/
#492
1!
#493
b11110100 +
b11110100 C
0/
#494
b11111000 %
b11111000 D
#496
0!
#497
1/
